{
  "id": "computer-science/algorithm/2024-02-23-byzantine-fault-tolerance",
  "title": "비잔틴 장애 허용 (Byzantine Fault Tolerance)",
  "description": "비잔틴 장애 허용",
  "source": "@site/docs/computer-science/algorithm/2024-02-23-byzantine-fault-tolerance.md",
  "sourceDirName": "computer-science/algorithm",
  "slug": "/computer-science/algorithm/2024-02-23-byzantine-fault-tolerance",
  "permalink": "/en/computer-science/algorithm/2024-02-23-byzantine-fault-tolerance",
  "draft": false,
  "unlisted": false,
  "tags": [
    {
      "label": "비잔틴 장애 허용",
      "permalink": "/en/tags/비잔틴-장애-허용"
    },
    {
      "label": "비트코인",
      "permalink": "/en/tags/비트코인"
    }
  ],
  "version": "current",
  "lastUpdatedBy": "Taegyeong Lee",
  "lastUpdatedAt": 1708670024000,
  "frontMatter": {
    "title": "비잔틴 장애 허용 (Byzantine Fault Tolerance)",
    "description": "비잔틴 장애 허용",
    "keywords": [
      "비잔틴 장애 허용",
      "비트코인"
    ],
    "tags": [
      "비잔틴 장애 허용",
      "비트코인"
    ]
  }
}